vinted_wrapper/__init__.py
vinted_wrapper/_version.py
vinted_wrapper/requester.py
vinted_wrapper/settings.py
vinted_wrapper/vinted.py
vinted_wrapper/items/__init__.py
vinted_wrapper/items/item.py
vinted_wrapper/items/items.py
vinted_wrapper_py-1.0.2.dist-info/METADATA
vinted_wrapper_py-1.0.2.dist-info/WHEEL
vinted_wrapper_py-1.0.2.dist-info/top_level.txt
vinted_wrapper_py-1.0.2.dist-info/RECORD
