Metadata-Version: 2.1
Name: vinted-wrapper-py
Version: 1.0.2
Summary: Simple Vinted Api for python 3
Home-page: https://github.com/EduardoHerreraM/vinted-wrapper-py
Author: EduardoHerreraM
License: UNKNOWN
Platform: UNKNOWN
Classifier: Programming Language :: Python :: 3
Classifier: Programming Language :: Python :: 3.6
Requires-Dist: requests
